rplanpy/__init__.py
rplanpy/data.py
rplanpy/metadata.py
rplanpy/plot.py
rplanpy/utils.py
rplanpy-0.1.1.dist-info/LICENSE
rplanpy-0.1.1.dist-info/METADATA
rplanpy-0.1.1.dist-info/WHEEL
rplanpy-0.1.1.dist-info/top_level.txt
rplanpy-0.1.1.dist-info/RECORD
