Metadata-Version: 2.1
Name: rplanpy
Version: 0.1.1
Summary: Set of python utilities to work with the RPLAN dataset from "[Data-driven Interior Plan Generation for Residential Buildings](https://doi.org/10.1145/3355089.3356556)" paper.
Home-page: https://github.com/unaisaralegui/rplanpy
Author: Unai Saralegui
Author-email: usaralegui@gmail.com
License: UNKNOWN
Platform: UNKNOWN
Classifier: Programming Language :: Python :: 3
Classifier: License :: OSI Approved :: MIT License
Classifier: Operating System :: OS Independent
License-File: LICENSE
Requires-Dist: imageio
Requires-Dist: numpy
Requires-Dist: matplotlib
Requires-Dist: networkx
Requires-Dist: scikit-image
Requires-Dist: scipy
